annotateai/__init__.py
annotateai/annotate.py
annotateai-0.2.0.dist-info/LICENSE
annotateai-0.2.0.dist-info/METADATA
annotateai-0.2.0.dist-info/WHEEL
annotateai-0.2.0.dist-info/top_level.txt
annotateai-0.2.0.dist-info/RECORD
