Metadata-Version: 2.1
Name: annotateai
Version: 0.2.0
Summary: Automatically annotate papers using LLMs
Home-page: https://github.com/neuml/annotateai
Author: NeuML
License: Apache 2.0: http://www.apache.org/licenses/LICENSE-2.0
Project-URL: Documentation, https://github.com/neuml/annotateai
Project-URL: Issue Tracker, https://github.com/neuml/annotateai/issues
Project-URL: Source Code, https://github.com/neuml/annotateai
Keywords: pdf highlight llm ai
Classifier: License :: OSI Approved :: Apache Software License
Classifier: Operating System :: OS Independent
Classifier: Programming Language :: Python :: 3
Classifier: Topic :: Scientific/Engineering :: Artificial Intelligence
Classifier: Topic :: Software Development
Classifier: Topic :: Utilities
Requires-Python: >=3.9
License-File: LICENSE
Requires-Dist: nltk (>=3.5)
Requires-Dist: tqdm (>=4.48.0)
Requires-Dist: txtai (>=8.1.0)
Requires-Dist: txtmarker (>=1.1.0)
